django_necormancer-0.1.11.dist-info/licenses/LICENSE
necromancer/cli/__init__.py
necromancer/cli/build_command.py
necromancer/cli/config.py
necromancer/cli/main.py
necromancer/cli/utils/__init__.py
necromancer/cli/utils/create_project.py
necromancer/cli/utils/setup_build_tools.py
necromancer/cli/utils/setup_package_manager.py
necromancer/core/build_tools/Make/Makefile
necromancer/core/project_templates/__init__.py
necromancer/core/project_templates/default/.env.example
necromancer/core/project_templates/default/__init__.py
necromancer/core/project_templates/default/asgi.py
necromancer/core/project_templates/default/manage.py
necromancer/core/project_templates/default/urls.py
necromancer/core/project_templates/default/wsgi.py
necromancer/core/project_templates/default/config/__init__.py
necromancer/core/project_templates/default/config/asgi.py
necromancer/core/project_templates/default/config/urls.py
necromancer/core/project_templates/default/config/wsgi.py
necromancer/core/project_templates/default/config/settings/__init__.py
necromancer/core/project_templates/default/config/settings/base.py
necromancer/core/project_templates/default/config/settings/dev.py
necromancer/core/project_templates/default/config/settings/prod.py
necromancer/core/requirements/pip-tools/base.in
necromancer/core/requirements/pip-tools/dev.in
necromancer/core/requirements/pip-tools/prod.in
django_necormancer-0.1.11.dist-info/METADATA
django_necormancer-0.1.11.dist-info/WHEEL
django_necormancer-0.1.11.dist-info/entry_points.txt
django_necormancer-0.1.11.dist-info/top_level.txt
django_necormancer-0.1.11.dist-info/RECORD
