Metadata-Version: 2.4
Name: django-necormancer
Version: 0.1.11
Summary: A short description of your package
Author-email: Byron Farrell <byronfarrell22@email.com>
License: MIT
Project-URL: Homepage, https://github.com/Byron-Farrell/necromancer
Requires-Python: >=3.7
License-File: LICENSE
Requires-Dist: typer
Requires-Dist: InquirerPy
Dynamic: license-file
